pyf/__init__.py
pyf/filetype.py
pyf/logger.py
pyf/options.py
pyf/pyf.py
pyf_programmers_find-0.9.0.dist-info/DESCRIPTION.rst
pyf_programmers_find-0.9.0.dist-info/entry_points.txt
pyf_programmers_find-0.9.0.dist-info/METADATA
pyf_programmers_find-0.9.0.dist-info/metadata.json
pyf_programmers_find-0.9.0.dist-info/RECORD
pyf_programmers_find-0.9.0.dist-info/top_level.txt
pyf_programmers_find-0.9.0.dist-info/WHEEL
