Metadata-Version: 2.0
Name: pyf-programmers-find
Version: 0.9.0
Summary: pyf: programmers find
Home-page: https://github.com/bnomis/pyf
Author: Simon Blanchard
Author-email: bnomis@gmail.com
License: MIT
Keywords: search,text,find
Platform: macosx
Platform: linux
Platform: unix
Classifier: Development Status :: 5 - Production/Stable
Classifier: Environment :: Console
Classifier: Intended Audience :: Developers
Classifier: Intended Audience :: System Administrators
Classifier: License :: OSI Approved :: MIT License
Classifier: Natural Language :: English
Classifier: Operating System :: POSIX
Classifier: Programming Language :: Python :: 2.7
Classifier: Programming Language :: Python :: 3.4
Classifier: Topic :: Software Development :: Build Tools
Classifier: Topic :: System :: Systems Administration
Classifier: Topic :: Text Processing
Classifier: Topic :: Utilities
